lazyurl/__init__.py
lazyurl/lazyurl.py
lazyurl-1.0.1.dist-info/METADATA
lazyurl-1.0.1.dist-info/WHEEL
lazyurl-1.0.1.dist-info/top_level.txt
lazyurl-1.0.1.dist-info/RECORD
