Metadata-Version: 2.4
Name: lazyurl
Version: 1.0.1
Summary: 解析url
Home-page: https://gitee.com/ZeroSeeker/lazyurl
Author: ZeroSeeker
Author-email: zeroseeker@foxmail.com
Classifier: Programming Language :: Python :: 3
Classifier: License :: OSI Approved :: MIT License
Classifier: Operating System :: OS Independent
Dynamic: author
Dynamic: author-email
Dynamic: classifier
Dynamic: description
Dynamic: description-content-type
Dynamic: home-page
Dynamic: summary
